snappea/__init__.py
snappea/admin.py
snappea/apps.py
snappea/datastructures.py
snappea/dbrouters.py
snappea/decorators.py
snappea/example_tasks.py
snappea/foreman.py
snappea/models.py
snappea/scmversion.py
snappea/sentry_sdk_extensions.py
snappea/settings.py
snappea/stats.py
snappea/tests.py
snappea/utils.py
snappea/views.py
snappea/management/__init__.py
snappea/management/commands/__init__.py
snappea/management/commands/checksnappea.py
snappea/management/commands/runsnappea.py
snappea/migrations/0001_initial.py
snappea/migrations/0002_create_models.py
snappea/migrations/0003_task_created_at.py
snappea/migrations/0004_task_snappea_tas_created_eb0824_idx.py
snappea/migrations/0005_stat.py
snappea/migrations/__init__.py
snappea-1.0.0.dist-info/licenses/LICENSE
snappea-1.0.0.dist-info/METADATA
snappea-1.0.0.dist-info/WHEEL
snappea-1.0.0.dist-info/top_level.txt
snappea-1.0.0.dist-info/RECORD
