Metadata-Version: 2.4
Name: snappea
Version: 1.0.0
Summary: MessageQueue-less task runner for Django
Author-email: "Bugsink B.V." <info@bugsink.com>
License-Expression: BSD-3-Clause
Project-URL: repository, https://github.com/bugsink/snappea/
Project-URL: documentation, https://www.bugsink.com/blog/snappea-design/
Project-URL: issues, https://github.com/bugsink/snappea/issues
Classifier: Framework :: Django
Classifier: Programming Language :: Python :: 3
Requires-Python: >=3.9
License-File: LICENSE
Requires-Dist: inotify_simple
Dynamic: license-file
